setup.cfg
setup.py
sweetpay/__init__.py
sweetpay/base.py
sweetpay/constants.py
sweetpay/errors.py
sweetpay/resources.py
sweetpay/utils.py
sweetpay.egg-info/PKG-INFO
sweetpay.egg-info/SOURCES.txt
sweetpay.egg-info/dependency_links.txt
sweetpay.egg-info/requires.txt
sweetpay.egg-info/top_level.txt