Metadata-Version: 1.1
Name: sweetpay
Version: 0.2.2
Summary: A SDK to talk with the Sweetpay APIs
Home-page: https://github.com/sweetpay/sweetpay-python
Author: David Buresund
Author-email: david.buresund@gmail.com
License: Apache 2
Download-URL: https://github.com/sweetpay/sweetpay-python/tarball/0.2.2
Keywords: sweetpay,checkout,payment
Platform: UNKNOWN
